Workbook

Sheet Overall Writeoffs
A1: Vehicle ownership and Operation (Business only) | B1: 20676.13
A3: 1099 Employees
A4: Bryan | B4: 29578.02
A5: Jameson | B5: 0
A6: Casey | B6: 19616.47
A7: Tony | B7: 0
A9: Month | B9: Deposits | C9: Expenses | D9: Bill Pay | G9: Difference | H9: Car Write off | I9: Difference | J9: 1099 | K9: Total Loss
A10: January | B10: 7113.78 | C10: 11377.59 | D10: 8590
A11: February | B11: 0 | C11: 25311.08 | D11: 7205.5
A12: March | B12: 3575 | C12: 22238.06 | D12: 4008
A13: April | B13: 15160 | C13: 19902.05 | D13: 5128.23
A14: May | B14: 99479.82 | C14: 7739.21 | D14: 2350
A15: June | B15: 8705 | C15: 9820.15 | D15: 2155.35
A16: July | B16: 29245.94 | C16: 13960.55 | D16: 6482.06
A17: August | B17: 40112.38 | C17: 5191.33 | D17: 2658.02
A18: September | B18: 38566.18 | C18: 5088.45 | D18: 1400
A19: October | B19: 33110.82 | C19: 16792.53 | D19: 7614
A20: November | B20: 46059.53 | C20: 2446.6 | D20: 210
A21: December | B21: 68733.48 | C21: 1477.77 | D21: 1393.33
A22: Total | B22: =SUM(B10:B21) | C22: =SUM(C10:C21) | D22: =SUM(D10:D21) | G22: =B22-C22-D22 | H22: 20676.13 | I22: =G22-H22 | J22: =SUM(B4:B7) | K22: =I22-J22

Sheet RAW_2025
A1: Date | B1: Description | C1: Amount | D1: Type
A2: 45659 | B2: Card Withdrawals - Debit Purchase - VISA On 123124 800-956-6310 IL 6122674711 $ | C2: 409.37 | D2: Debit
A3: 45659 | B3: Other Withdrawals - Zelle Instant PMT To Nadia Session $ | C3: 247 | D3: Debit
A4: 45660 | B4: Other Withdrawals - Zelle Instant PMT To Brian Davis | C4: 1120 | D4: Debit
A5: 45660 | B5: Other Withdrawals - Zelle Instant PMT To Casey Williamson | C5: 600 | D5: Debit
A6: 45663 | B6: Other Withdrawals - Electronic Withdrawal To CEFCU TEL DEBIT | C6: 1042.46 | D6: Debit
A7: 45664 | B7: Other Withdrawals - Mobile Banking Transfer To Account 152316874980 | C7: 15 | D7: Debit
A8: 45665 | B8: Card Withdrawals - Debit Purchase - VISA On 010725 O FALLON IL 7001446395 | C8: 2.19 | D8: Debit
A9: 45665 | B9: Other Deposits - Debit Purchase Ret - VISA On 010725 8664244197 IL 7063781288 $ | C9: 13.78 | D9: Credit
A10: 45665 | B10: Other Withdrawals - Electronic Withdrawal To Mission Lane LLC | C10: 67.44 | D10: Debit
A11: 45666 | B11: Card Withdrawals - Debit Purchase - VISA On 010725 618-2869595 IL 8109867096 | C11: 440 | D11: Debit
A12: 45666 | B12: Other Withdrawals - Zelle Instant PMT To Brian Davis | C12: 80 | D12: Debit
A13: 45667 | B13: Card Withdrawals - Debit Purchase MOTOMART FREEBURG IL | C13: 61.97 | D13: Debit
... A576: 46000 | B576: Other Withdrawals - Mobile Banking Transfer To Account 152316875235 | C576: 200 | D576: Debit

Sheet CATEGORIZED_2025
A1: Date | B1: Description | C1: Amount | D1: Type | E1: Category | F1: Original Group | G1: Final Group | H1: Manual Override | I1: Override Note | J1: Contractor | L1: WARNING: Changing Final Group may impact tax reporting. Confirm with tax professional.
A2: 45659 | B2: Card Withdrawals - Debit Purchase - VISA On 123124 800-956-6310 IL 6122674711 $ | C2: 409.37 | D2: Debit | E2: Tools | F2: =IF(E2="Income","Revenue",IF(OR(E2="Materials",E2="Labor",E2="Dump Fees"),"COGS",IF(OR(E2="Fuel",E2="Insurance",E2="Tools",E2="Repairs"),"Expense","Non-Deductible"))) | G2: Expense | H2: =IF(G2<>F2,"YES","NO")
A3: 45659 | B3: Other Withdrawals - Zelle Instant PMT To Nadia Session $ | C3: 247 | D3: Debit | E3: Tools | F3: =IF(E3="Income","Revenue",IF(OR(E3="Materials",E3="Labor",E3="Dump Fees"),"COGS",IF(OR(E3="Fuel",E3="Insurance",E3="Tools",E3="Repairs"),"Expense","Non-Deductible"))) | G3: Expense | H3: =IF(G3<>F3,"YES","NO")
A4: 45660 | B4: Other Withdrawals - Zelle Instant PMT To Brian Davis | C4: 1120 | D4: Debit | E4: Labor | F4: =IF(E4="Income","Revenue",IF(OR(E4="Materials",E4="Labor",E4="Dump Fees"),"COGS",IF(OR(E4="Fuel",E4="Insurance",E4="Tools",E4="Repairs"),"Expense","Non-Deductible"))) | G4: COGS | H4: =IF(G4<>F4,"YES","NO") | J4: Bryan
A5: 45660 | B5: Other Withdrawals - Zelle Instant PMT To Casey Williamson | C5: 600 | D5: Debit | E5: Labor | F5: =IF(E5="Income","Revenue",IF(OR(E5="Materials",E5="Labor",E5="Dump Fees"),"COGS",IF(OR(E5="Fuel",E5="Insurance",E5="Tools",E5="Repairs"),"Expense","Non-Deductible"))) | G5: COGS | H5: =IF(G5<>F5,"YES","NO") | J5: Casey
A6: 45663 | B6: Other Withdrawals - Electronic Withdrawal To CEFCU TEL DEBIT | C6: 1042.46 | D6: Debit | E6: Tools | F6: =IF(E6="Income","Revenue",IF(OR(E6="Materials",E6="Labor",E6="Dump Fees"),"COGS",IF(OR(E6="Fuel",E6="Insurance",E6="Tools",E6="Repairs"),"Expense","Non-Deductible"))) | G6: Expense | H6: =IF(G6<>F6,"YES","NO")
A7: 45664 | B7: Other Withdrawals - Mobile Banking Transfer To Account 152316874980 | C7: 15 | D7: Debit | E7: Transfer | F7: =IF(E7="Income","Revenue",IF(OR(E7="Materials",E7="Labor",E7="Dump Fees"),"COGS",IF(OR(E7="Fuel",E7="Insurance",E7="Tools",E7="Repairs"),"Expense","Non-Deductible"))) | G7: Non-Deductible | H7: =IF(G7<>F7,"YES","NO")
A8: 45665 | B8: Card Withdrawals - Debit Purchase - VISA On 010725 O FALLON IL 7001446395 | C8: 2.19 | D8: Debit | E8: Tools | F8: =IF(E8="Income","Revenue",IF(OR(E8="Materials",E8="Labor",E8="Dump Fees"),"COGS",IF(OR(E8="Fuel",E8="Insurance",E8="Tools",E8="Repairs"),"Expense","Non-Deductible"))) | G8: Expense | H8: =IF(G8<>F8,"YES","NO")
A9: 45665 | B9: Other Deposits - Debit Purchase Ret - VISA On 010725 8664244197 IL 7063781288 $ | C9: 13.78 | D9: Credit | E9: Income | F9: =IF(E9="Income","Revenue",IF(OR(E9="Materials",E9="Labor",E9="Dump Fees"),"COGS",IF(OR(E9="Fuel",E9="Insurance",E9="Tools",E9="Repairs"),"Expense","Non-Deductible"))) | G9: Revenue | H9: =IF(G9<>F9,"YES","NO")
A10: 45665 | B10: Other Withdrawals - Electronic Withdrawal To Mission Lane LLC | C10: 67.44 | D10: Debit | E10: Tools | F10: =IF(E10="Income","Revenue",IF(OR(E10="Materials",E10="Labor",E10="Dump Fees"),"COGS",IF(OR(E10="Fuel",E10="Insurance",E10="Tools",E10="Repairs"),"Expense","Non-Deductible"))) | G10: Expense | H10: =IF(G10<>F10,"YES","NO")
A11: 45666 | B11: Card Withdrawals - Debit Purchase - VISA On 010725 618-2869595 IL 8109867096 | C11: 440 | D11: Debit | E11: Tools | F11: =IF(E11="Income","Revenue",IF(OR(E11="Materials",E11="Labor",E11="Dump Fees"),"COGS",IF(OR(E11="Fuel",E11="Insurance",E11="Tools",E11="Repairs"),"Expense","Non-Deductible"))) | G11: Expense | H11: =IF(G11<>F11,"YES","NO")
A12: 45666 | B12: Other Withdrawals - Zelle Instant PMT To Brian Davis | C12: 80 | D12: Debit | E12: Labor | F12: =IF(E12="Income","Revenue",IF(OR(E12="Materials",E12="Labor",E12="Dump Fees"),"COGS",IF(OR(E12="Fuel",E12="Insurance",E12="Tools",E12="Repairs"),"Expense","Non-Deductible"))) | G12: COGS | H12: =IF(G12<>F12,"YES","NO") | J12: Bryan
A13: 45667 | B13: Card Withdrawals - Debit Purchase MOTOMART FREEBURG IL | C13: 61.97 | D13: Debit | E13: Tools | F13: =IF(E13="Income","Revenue",IF(OR(E13="Materials",E13="Labor",E13="Dump Fees"),"COGS",IF(OR(E13="Fuel",E13="Insurance",E13="Tools",E13="Repairs"),"Expense","Non-Deductible"))) | G13: Expense | H13: =IF(G13<>F13,"YES","NO")
A14: 45667 | B14: Other Withdrawals - Mobile Banking Transfer To Account 152316875235 | C14: 300 | D14: Debit | E14: Transfer | F14: =IF(E14="Income","Revenue",IF(OR(E14="Materials",E14="Labor",E14="Dump Fees"),"COGS",IF(OR(E14="Fuel",E14="Insurance",E14="Tools",E14="Repairs"),"Expense","Non-Deductible"))) | G14: Non-Deductible | H14: =IF(G14<>F14,"YES","NO")
A15: 45667 | B15: Other Withdrawals - Zelle Instant PMT To Brian Davis | C15: 945 | D15: Debit | E15: Labor | F15: =IF(E15="Income","Revenue",IF(OR(E15="Materials",E15="Labor",E15="Dump Fees"),"COGS",IF(OR(E15="Fuel",E15="Insurance",E15="Tools",E15="Repairs"),"Expense","Non-Deductible"))) | G15: COGS | H15: =IF(G15<>F15,"YES","NO") | J15: Bryan
A16: 45667 | B16: Other Withdrawals - Zelle Instant PMT To Casey Williamson | C16: 575 | D16: Debit | E16: Labor | F16: =IF(E16="Income","Revenue",IF(OR(E16="Materials",E16="Labor",E16="Dump Fees"),"COGS",IF(OR(E16="Fuel",E16="Insurance",E16="Tools",E16="Repairs"),"Expense","Non-Deductible"))) | G16: COGS | H16: =IF(G16<>F16,"YES","NO") | J16: Casey
A17: 45670 | B17: Card Withdrawals - ATM Withdrawal 300 S GREEN MOUN BELLEVILLE IL | C17: 103.95 | D17: Debit | E17: Tools | F17: =IF(E17="Income","Revenue",IF(OR(E17="Materials",E17="Labor",E17="Dump Fees"),"COGS",IF(OR(E17="Fuel",E17="Insurance",E17="Tools",E17="Repairs"),"Expense","Non-Deductible"))) | G17: Expense | H17: =IF(G17<>F17,"YES","NO")
A18: 45670 | B18: Card Withdrawals - Debit Purchase - VISA On 011125 Visa Direct NY 1000183320 | C18: 100 | D18: Debit | E18: Tools | F18: =IF(E18="Income","Revenue",IF(OR(E18="Materials",E18="Labor",E18="Dump Fees"),"COGS",IF(OR(E18="Fuel",E18="Insurance",E18="Tools",E18="Repairs"),"Expense","Non-Deductible"))) | G18: Expense | H18: =IF(G18<>F18,"YES","NO")
A19: 45670 | B19: Card Withdrawals - Debit Purchase CIRCLE K # 01361 BELLEVILLE IL | C19: 27.01 | D19: Debit | E19: Tools | F19: =IF(E19="Income","Revenue",IF(OR(E19="Materials",E19="Labor",E19="Dump Fees"),"COGS",IF(OR(E19="Fuel",E19="Insurance",E19="Tools",E19="Repairs"),"Expense","Non-Deductible"))) | G19: Expense | H19: =IF(G19<>F19,"YES","NO")
A20: 45670 | B20: Card Withdrawals - Debit Purchase MOTOMART FREEBURG IL | C20: 87.64 | D20: Debit | E20: Tools | F20: =IF(E20="Income","Revenue",IF(OR(E20="Materials",E20="Labor",E20="Dump Fees"),"COGS",IF(OR(E20="Fuel",E20="Insurance",E20="Tools",E20="Repairs"),"Expense","Non-Deductible"))) | G20: Expense | H20: =IF(G20<>F20,"YES","NO")
A21: 45670 | B21: Card Withdrawals - Debit Purchase THE HOME DEPOT # BELLEVILLE IL 6901111158 | C21: 371.21 | D21: Debit | E21: Materials | F21: =IF(E21="Income","Revenue",IF(OR(E21="Materials",E21="Labor",E21="Dump Fees"),"COGS",IF(OR(E21="Fuel",E21="Insurance",E21="Tools",E21="Repairs"),"Expense","Non-Deductible"))) | G21: COGS | H21: =IF(G21<>F21,"YES","NO")
A22: 45670 | B22: Card Withdrawals - Fee ATM Withdrawal At Other Network 1300000717 $ | C22: 2.5 | D22: Debit | E22: Tools | F22: =IF(E22="Income","Revenue",IF(OR(E22="Materials",E22="Labor",E22="Dump Fees"),"COGS",IF(OR(E22="Fuel",E22="Insurance",E22="Tools",E22="Repairs"),"Expense","Non-Deductible"))) | G22: Expense | H22: =IF(G22<>F22,"YES","NO")
A23: 45670 | B23: Other Withdrawals - Electronic Withdrawal To MERCURY CARD FBT | C23: 573.53 | D23: Debit | E23: Tools | F23: =IF(E23="Income","Revenue",IF(OR(E23="Materials",E23="Labor",E23="Dump Fees"),"COGS",IF(OR(E23="Fuel",E23="Insurance",E23="Tools",E23="Repairs"),"Expense","Non-Deductible"))) | G23: Expense | H23: =IF(G23<>F23,"YES","NO")
A24: 45672 | B24: Card Withdrawals - Debit Purchase - VISA On 011425 618-2330303 IL 5006499752 | C24: 74.54 | D24: Debit | E24: Tools | F24: =IF(E24="Income","Revenue",IF(OR(E24="Materials",E24="Labor",E24="Dump Fees"),"COGS",IF(OR(E24="Fuel",E24="Insurance",E24="Tools",E24="Repairs"),"Expense","Non-Deductible"))) | G24: Expense | H24: =IF(G24<>F24,"YES","NO")
A25: 45672 | B25: Card Withdrawals - Debit Purchase - VISA On 011425 FREEBURG IL 4720240094 | C25: 3.6 | D25: Debit | E25: Tools | F25: =IF(E25="Income","Revenue",IF(OR(E25="Materials",E25="Labor",E25="Dump Fees"),"COGS",IF(OR(E25="Fuel",E25="Insurance",E25="Tools",E25="Repairs"),"Expense","Non-Deductible"))) | G25: Expense | H25: =IF(G25<>F25,"YES","NO")
A26: 45672 | B26: Card Withdrawals - Debit Purchase CIRCLE K # 01343 SHILOH IL | C26: 28.98 | D26: Debit | E26: Tools | F26: =IF(E26="Income","Revenue",IF(OR(E26="Materials",E26="Labor",E26="Dump Fees"),"COGS",IF(OR(E26="Fuel",E26="Insurance",E26="Tools",E26="Repairs"),"Expense","Non-Deductible"))) | G26: Expense | H26: =IF(G26<>F26,"YES","NO")
A27: 45672 | B27: Other Deposits - Mobile Check Deposit 8613623522 | C27: 4400 | D27: Credit | E27: Income | F27: =IF(E27="Income","Revenue",IF(OR(E27="Materials",E27="Labor",E27="Dump Fees"),"COGS",IF(OR(E27="Fuel",E27="Insurance",E27="Tools",E27="Repairs"),"Expense","Non-Deductible"))) | G27: Revenue | H27: =IF(G27<>F27,"YES","NO")
A28: 45672 | B28: Other Withdrawals - Analysis Service Charge 1600000000 | C28: 16 | D28: Debit | E28: Repairs | F28: =IF(E28="Income","Revenue",IF(OR(E28="Materials",E28="Labor",E28="Dump Fees"),"COGS",IF(OR(E28="Fuel",E28="Insurance",E28="Tools",E28="Repairs"),"Expense","Non-Deductible"))) | G28: Expense | H28: =IF(G28<>F28,"YES","NO")
... A39: 45674 | B39: Other Withdrawals - Electronic Withdrawal To MIDLAND MTG | C39: 1089.56 | D39: Debit | E39: Tools | F39: =IF(E39="Income","Revenue",IF(OR(E39="Materials",E39="Labor",E39="Dump Fees"),"COGS",IF(OR(E39="Fuel",E39="Insurance",E39="Tools",E39="Repairs"),"Expense","Non-Deductible"))) | G39: Expense | H39: =IF(G39<>F39,"YES","NO")
A40: 45674 | B40: Other Withdrawals - Zelle Instant PMT To BRIAN DAVIS | C40: 1330 | D40: Debit | E40: Labor | F40: =IF(E40="Income","Revenue",IF(OR(E40="Materials",E40="Labor",E40="Dump Fees"),"COGS",IF(OR(E40="Fuel",E40="Insurance",E40="Tools",E40="Repairs"),"Expense","Non-Deductible"))) | G40: COGS | H40: =IF(G40<>F40,"YES","NO") | J40: Bryan
A41: 45674 | B41: Other Withdrawals - Zelle Instant PMT To Casey Williamson | C41: 600 | D41: Debit | E41: Labor | F41: =IF(E41="Income","Revenue",IF(OR(E41="Materials",E41="Labor",E41="Dump Fees"),"COGS",IF(OR(E41="Fuel",E41="Insurance",E41="Tools",E41="Repairs"),"Expense","Non-Deductible"))) | G41: COGS | H41: =IF(G41<>F41,"YES","NO") | J41: Casey
A42: 45674 | B42: Other Withdrawals - Zelle Instant PMT To Nadia Session | C42: 100 | D42: Debit | E42: Tools | F42: =IF(E42="Income","Revenue",IF(OR(E42="Materials",E42="Labor",E42="Dump Fees"),"COGS",IF(OR(E42="Fuel",E42="Insurance",E42="Tools",E42="Repairs"),"Expense","Non-Deductible"))) | G42: Expense | H42: =IF(G42<>F42,"YES","NO")
A43: 45678 | B43: Card Withdrawals - Debit Purchase DOLLAR-GENERAL # FREEBURG IL 2301191431 | C43: 87.41 | D43: Debit | E43: Tools | F43: =IF(E43="Income","Revenue",IF(OR(E43="Materials",E43="Labor",E43="Dump Fees"),"COGS",IF(OR(E43="Fuel",E43="Insurance",E43="Tools",E43="Repairs"),"Expense","Non-Deductible"))) | G43: Expense | H43: =IF(G43<>F43,"YES","NO")
A44: 45678 | B44: Card Withdrawals - Debit Purchase verifyvend855-55 PROVIDENCE RI 1201201605 | C44: 236 | D44: Debit | E44: Tools | F44: =IF(E44="Income","Revenue",IF(OR(E44="Materials",E44="Labor",E44="Dump Fees"),"COGS",IF(OR(E44="Fuel",E44="Insurance",E44="Tools",E44="Repairs"),"Expense","Non-Deductible"))) | G44: Expense | H44: =IF(G44<>F44,"YES","NO")
A45: 45680 | B45: Other Withdrawals - Mobile Banking Transfer To Account 152316874980 | C45: 66 | D45: Debit | E45: Transfer | F45: =IF(E45="Income","Revenue",IF(OR(E45="Materials",E45="Labor",E45="Dump Fees"),"COGS",IF(OR(E45="Fuel",E45="Insurance",E45="Tools",E45="Repairs"),"Expense","Non-Deductible"))) | G45: Non-Deductible | H45: =IF(G45<>F45,"YES","NO")
A46: 45681 | B46: Other Withdrawals - Mobile Banking Transfer To Account 152316875235 | C46: 850 | D46: Debit | E46: Transfer | F46: =IF(E46="Income","Revenue",IF(OR(E46="Materials",E46="Labor",E46="Dump Fees"),"COGS",IF(OR(E46="Fuel",E46="Insurance",E46="Tools",E46="Repairs"),"Expense","Non-Deductible"))) | G46: Non-Deductible | H46: =IF(G46<>F46,"YES","NO")
A47: 45681 | B47: Other Withdrawals - Zelle Instant PMT To Brian Davis | C47: 890 | D47: Debit | E47: Labor | F47: =IF(E47="Income","Revenue",IF(OR(E47="Materials",E47="Labor",E47="Dump Fees"),"COGS",IF(OR(E47="Fuel",E47="Insurance",E47="Tools",E47="Repairs"),"Expense","Non-Deductible"))) | G47: COGS | H47: =IF(G47<>F47,"YES","NO") | J47: Bryan
A48: 45681 | B48: Other Withdrawals - Zelle Instant PMT To Casey Williamson | C48: 200 | D48: Debit | E48: Labor | F48: =IF(E48="Income","Revenue",IF(OR(E48="Materials",E48="Labor",E48="Dump Fees"),"COGS",IF(OR(E48="Fuel",E48="Insurance",E48="Tools",E48="Repairs"),"Expense","Non-Deductible"))) | G48: COGS | H48: =IF(G48<>F48,"YES","NO") | J48: Casey
A49: 45684 | B49: Card Withdrawals - Debit Purchase MOTOMART FREEBURG IL | C49: 86.57 | D49: Debit | E49: Tools | F49: =IF(E49="Income","Revenue",IF(OR(E49="Materials",E49="Labor",E49="Dump Fees"),"COGS",IF(OR(E49="Fuel",E49="Insurance",E49="Tools",E49="Repairs"),"Expense","Non-Deductible"))) | G49: Expense | H49: =IF(G49<>F49,"YES","NO")
A50: 45684 | B50: Card Withdrawals - Recurring Debit Purchase On 012525 888-270-2644 IN 6101039921 | C50: 817.5 | D50: Debit | E50: Tools | F50: =IF(E50="Income","Revenue",IF(OR(E50="Materials",E50="Labor",E50="Dump Fees"),"COGS",IF(OR(E50="Fuel",E50="Insurance",E50="Tools",E50="Repairs"),"Expense","Non-Deductible"))) | G50: Expense | H50: =IF(G50<>F50,"YES","NO")
A51: 45685 | B51: Card Withdrawals - Debit Purchase MOTOMART FREEBURG IL | C51: 82.94 | D51: Debit | E51: Tools | F51: =IF(E51="Income","Revenue",IF(OR(E51="Materials",E51="Labor",E51="Dump Fees"),"COGS",IF(OR(E51="Fuel",E51="Insurance",E51="Tools",E51="Repairs"),"Expense","Non-Deductible"))) | G51: Expense | H51: =IF(G51<>F51,"YES","NO")
A52: 45688 | B52: Card Withdrawals - Recurring Debit Purchase On 013025 800-956-6310 IL 0140734882 | C52: 328.76 | D52: Debit | E52: Tools | F52: =IF(E52="Income","Revenue",IF(OR(E52="Materials",E52="Labor",E52="Dump Fees"),"COGS",IF(OR(E52="Fuel",E52="Insurance",E52="Tools",E52="Repairs"),"Expense","Non-Deductible"))) | G52: Expense | H52: =IF(G52<>F52,"YES","NO")
A53: 45688 | B53: Other Withdrawals - Customer Withdrawal 9213013769 | C53: 2000 | D53: Debit | E53: Tools | F53: =IF(E53="Income","Revenue",IF(OR(E53="Materials",E53="Labor",E53="Dump Fees"),"COGS",IF(OR(E53="Fuel",E53="Insurance",E53="Tools",E53="Repairs"),"Expense","Non-Deductible"))) | G53: Expense | H53: =IF(G53<>F53,"YES","NO")
A54: 45688 | B54: Other Withdrawals - Mobile Banking Transfer To Account 152316875235 | C54: 750 | D54: Debit | E54: Transfer | F54: =IF(E54="Income","Revenue",IF(OR(E54="Materials",E54="Labor",E54="Dump Fees"),"COGS",IF(OR(E54="Fuel",E54="Insurance",E54="Tools",E54="Repairs"),"Expense","Non-Deductible"))) | G54: Non-Deductible | H54: =IF(G54<>F54,"YES","NO")
A55: 45688 | B55: Other Withdrawals - Zelle Instant PMT To Brian Davis | C55: 1450 | D55: Debit | E55: Labor | F55: =IF(E55="Income","Revenue",IF(OR(E55="Materials",E55="Labor",E55="Dump Fees"),"COGS",IF(OR(E55="Fuel",E55="Insurance",E55="Tools",E55="Repairs"),"Expense","Non-Deductible"))) | G55: COGS | H55: =IF(G55<>F55,"YES","NO") | J55: Bryan
A56: 45688 | B56: Other Withdrawals - Zelle Instant PMT To Casey Williamson | C56: 800 | D56: Debit | E56: Labor | F56: =IF(E56="Income","Revenue",IF(OR(E56="Materials",E56="Labor",E56="Dump Fees"),"COGS",IF(OR(E56="Fuel",E56="Insurance",E56="Tools",E56="Repairs"),"Expense","Non-Deductible"))) | G56: COGS | H56: =IF(G56<>F56,"YES","NO") | J56: Casey
A57: 45691 | B57: Card Withdrawals - ATM Withdrawal 1291 OLD BALDWIN NEW ATHENS IL | C57: 203.25 | D57: Debit | E57: Tools | F57: =IF(E57="Income","Revenue",IF(OR(E57="Materials",E57="Labor",E57="Dump Fees"),"COGS",IF(OR(E57="Fuel",E57="Insurance",E57="Tools",E57="Repairs"),"Expense","Non-Deductible"))) | G57: Expense | H57: =IF(G57<>F57,"YES","NO")
A58: 45691 | B58: Card Withdrawals - ATM Withdrawal 301 SALEM PL FAIRVIEW HEI IL | C58: 103.95 | D58: Debit | E58: Tools | F58: =IF(E58="Income","Revenue",IF(OR(E58="Materials",E58="Labor",E58="Dump Fees"),"COGS",IF(OR(E58="Fuel",E58="Insurance",E58="Tools",E58="Repairs"),"Expense","Non-Deductible"))) | G58: Expense | H58: =IF(G58<>F58,"YES","NO")
A59: 45691 | B59: Card Withdrawals - Debit Purchase CIRCLE K 01594 3 FAIRVIEW HEIIL $ | C59: 93.23 | D59: Debit | E59: Tools | F59: =IF(E59="Income","Revenue",IF(OR(E59="Materials",E59="Labor",E59="Dump Fees"),"COGS",IF(OR(E59="Fuel",E59="Insurance",E59="Tools",E59="Repairs"),"Expense","Non-Deductible"))) | G59: Expense | H59: =IF(G59<>F59,"YES","NO")
A60: 45691 | B60: Card Withdrawals - Fee ATM Withdrawal At Other Network 0300000324 $ | C60: 2.5 | D60: Debit | E60: Tools | F60: =IF(E60="Income","Revenue",IF(OR(E60="Materials",E60="Labor",E60="Dump Fees"),"COGS",IF(OR(E60="Fuel",E60="Insurance",E60="Tools",E60="Repairs"),"Expense","Non-Deductible"))) | G60: Expense | H60: =IF(G60<>F60,"YES","NO")
A61: 45691 | B61: Card Withdrawals - Fee ATM Withdrawal At Other Network 0300000325 | C61: 2.5 | D61: Debit | E61: Tools | F61: =IF(E61="Income","Revenue",IF(OR(E61="Materials",E61="Labor",E61="Dump Fees"),"COGS",IF(OR(E61="Fuel",E61="Insurance",E61="Tools",E61="Repairs"),"Expense","Non-Deductible"))) | G61: Expense | H61: =IF(G61<>F61,"YES","NO")
A62: 45691 | B62: Other Withdrawals - Electronic Withdrawal To DISCOVER | C62: 3906.11 | D62: Debit | E62: Tools | F62: =IF(E62="Income","Revenue",IF(OR(E62="Materials",E62="Labor",E62="Dump Fees"),"COGS",IF(OR(E62="Fuel",E62="Insurance",E62="Tools",E62="Repairs"),"Expense","Non-Deductible"))) | G62: Expense | H62: =IF(G62<>F62,"YES","NO")
A63: 45691 | B63: Other Withdrawals - Electronic Withdrawal To DISCOVER $ | C63: 34.85 | D63: Debit | E63: Tools | F63: =IF(E63="Income","Revenue",IF(OR(E63="Materials",E63="Labor",E63="Dump Fees"),"COGS",IF(OR(E63="Fuel",E63="Insurance",E63="Tools",E63="Repairs"),"Expense","Non-Deductible"))) | G63: Expense | H63: =IF(G63<>F63,"YES","NO")
A64: 45691 | B64: Other Withdrawals - Electronic Withdrawal To MERCURY CARD FBT | C64: 1364.91 | D64: Debit | E64: Tools | F64: =IF(E64="Income","Revenue",IF(OR(E64="Materials",E64="Labor",E64="Dump Fees"),"COGS",IF(OR(E64="Fuel",E64="Insurance",E64="Tools",E64="Repairs"),"Expense","Non-Deductible"))) | G64: Expense | H64: =IF(G64<>F64,"YES","NO")
A65: 45691 | B65: Other Withdrawals - Electronic Withdrawal To Mission Lane LLC | C65: 1110.22 | D65: Debit | E65: Tools | F65: =IF(E65="Income","Revenue",IF(OR(E65="Materials",E65="Labor",E65="Dump Fees"),"COGS",IF(OR(E65="Fuel",E65="Insurance",E65="Tools",E65="Repairs"),"Expense","Non-Deductible"))) | G65: Expense | H65: =IF(G65<>F65,"YES","NO")
A66: 45691 | B66: Other Withdrawals - Mobile Banking Payment To Credit Card *************3424 | C66: 1979.96 | D66: Debit | E66: Fuel | F66: =IF(E66="Income","Revenue",IF(OR(E66="Materials",E66="Labor",E66="Dump Fees"),"COGS",IF(OR(E66="Fuel",E66="Insurance",E66="Tools",E66="Repairs"),"Expense","Non-Deductible"))) | G66: Expense | H66: =IF(G66<>F66,"YES","NO")
A67: 45691 | B67: Other Withdrawals - Mobile Banking Transfer To Account 152316875235 | C67: 288.8 | D67: Debit | E67: Transfer | F67: =IF(E67="Income","Revenue",IF(OR(E67="Materials",E67="Labor",E67="Dump Fees"),"COGS",IF(OR(E67="Fuel",E67="Insurance",E67="Tools",E67="Repairs"),"Expense","Non-Deductible"))) | G67: Non-Deductible | H67: =IF(G67<>F67,"YES","NO")
A68: 45692 | B68: Other Withdrawals - Electronic Withdrawal To CEFCU TEL DEBIT | C68: 1042.46 | D68: Debit | E68: Tools | F68: =IF(E68="Income","Revenue",IF(OR(E68="Materials",E68="Labor",E68="Dump Fees"),"COGS",IF(OR(E68="Fuel",E68="Insurance",E68="Tools",E68="Repairs"),"Expense","Non-Deductible"))) | G68: Expense | H68: =IF(G68<>F68,"YES","NO")
... A70: 45694 | B70: Card Withdrawals - Debit Purchase verifyvend855-55 PROVIDENCE RI 0402061511 | C70: 183 | D70: Debit | E70: Tools | F70: =IF(E70="Income","Revenue",IF(OR(E70="Materials",E70="Labor",E70="Dump Fees"),"COGS",IF(OR(E70="Fuel",E70="Insurance",E70="Tools",E70="Repairs"),"Expense","Non-Deductible"))) | G70: Expense | H70: =IF(G70<>F70,"YES","NO")
A71: 45695 | B71: Card Withdrawals - Debit Purchase CASEYS #3252 129 NEW ATHENS IL 6202061905 | C71: 12.5 | D71: Debit | E71: Labor | F71: =IF(E71="Income","Revenue",IF(OR(E71="Materials",E71="Labor",E71="Dump Fees"),"COGS",IF(OR(E71="Fuel",E71="Insurance",E71="Tools",E71="Repairs"),"Expense","Non-Deductible"))) | G71: COGS | H71: =IF(G71<>F71,"YES","NO") | J71: Casey
A72: 45695 | B72: Card Withdrawals - Debit Purchase MOTOMART FREEBURG IL | C72: 85.7 | D72: Debit | E72: Tools | F72: =IF(E72="Income","Revenue",IF(OR(E72="Materials",E72="Labor",E72="Dump Fees"),"COGS",IF(OR(E72="Fuel",E72="Insurance",E72="Tools",E72="Repairs"),"Expense","Non-Deductible"))) | G72: Expense | H72: =IF(G72<>F72,"YES","NO")
A73: 45695 | B73: Other Withdrawals - Zelle Instant PMT To Brian Davis | C73: 1380 | D73: Debit | E73: Labor | F73: =IF(E73="Income","Revenue",IF(OR(E73="Materials",E73="Labor",E73="Dump Fees"),"COGS",IF(OR(E73="Fuel",E73="Insurance",E73="Tools",E73="Repairs"),"Expense","Non-Deductible"))) | G73: COGS | H73: =IF(G73<>F73,"YES","NO") | J73: Bryan
A74: 45695 | B74: Other Withdrawals - Zelle Instant PMT To Casey Williamson | C74: 950 | D74: Debit | E74: Labor | F74: =IF(E74="Income","Revenue",IF(OR(E74="Materials",E74="Labor",E74="Dump Fees"),"COGS",IF(OR(E74="Fuel",E74="Insurance",E74="Tools",E74="Repairs"),"Expense","Non-Deductible"))) | G74: COGS | H74: =IF(G74<>F74,"YES","NO") | J74: Casey
A75: 45695 | B75: Other Withdrawals - Zelle Instant PMT To Tabitha Session | C75: 500 | D75: Debit | E75: Tools | F75: =IF(E75="Income","Revenue",IF(OR(E75="Materials",E75="Labor",E75="Dump Fees"),"COGS",IF(OR(E75="Fuel",E75="Insurance",E75="Tools",E75="Repairs"),"Expense","Non-Deductible"))) | G75: Expense | H75: =IF(G75<>F75,"YES","NO")
A76: 45698 | B76: Card Withdrawals - Debit Purchase - VISA On 020625 SHILOH IL 8236407155 | C76: 22.5 | D76: Debit | E76: Tools | F76: =IF(E76="Income","Revenue",IF(OR(E76="Materials",E76="Labor",E76="Dump Fees"),"COGS",IF(OR(E76="Fuel",E76="Insurance",E76="Tools",E76="Repairs"),"Expense","Non-Deductible"))) | G76: Expense | H76: =IF(G76<>F76,"YES","NO")
A77: 45698 | B77: Other Withdrawals - Zelle Instant PMT To Nadia Session | C77: 243 | D77: Debit | E77: Tools | F77: =IF(E77="Income","Revenue",IF(OR(E77="Materials",E77="Labor",E77="Dump Fees"),"COGS",IF(OR(E77="Fuel",E77="Insurance",E77="Tools",E77="Repairs"),"Expense","Non-Deductible"))) | G77: Expense | H77: =IF(G77<>F77,"YES","NO")
A78: 45698 | B78: Other Withdrawals - Zelle Instant PMT To Tabitha Session | C78: 60 | D78: Debit | E78: Tools | F78: =IF(E78="Income","Revenue",IF(OR(E78="Materials",E78="Labor",E78="Dump Fees"),"COGS",IF(OR(E78="Fuel",E78="Insurance",E78="Tools",E78="Repairs"),"Expense","Non-Deductible"))) | G78: Expense | H78: =IF(G78<>F78,"YES","NO")
A79: 45698 | B79: Other Withdrawals - Zelle Instant PMT To Tabitha Session | C79: 70 | D79: Debit | E79: Tools | F79: =IF(E79="Income","Revenue",IF(OR(E79="Materials",E79="Labor",E79="Dump Fees"),"COGS",IF(OR(E79="Fuel",E79="Insurance",E79="Tools",E79="Repairs"),"Expense","Non-Deductible"))) | G79: Expense | H79: =IF(G79<>F79,"YES","NO")
A80: 45698 | B80: Other Withdrawals - Zelle Instant PMT To Tabitha Session | C80: 140 | D80: Debit | E80: Tools | F80: =IF(E80="Income","Revenue",IF(OR(E80="Materials",E80="Labor",E80="Dump Fees"),"COGS",IF(OR(E80="Fuel",E80="Insurance",E80="Tools",E80="Repairs"),"Expense","Non-Deductible"))) | G80: Expense | H80: =IF(G80<>F80,"YES","NO")
A81: 45698 | B81: Other Withdrawals - Zelle Instant PMT To Tabitha Session | C81: 250 | D81: Debit | E81: Tools | F81: =IF(E81="Income","Revenue",IF(OR(E81="Materials",E81="Labor",E81="Dump Fees"),"COGS",IF(OR(E81="Fuel",E81="Insurance",E81="Tools",E81="Repairs"),"Expense","Non-Deductible"))) | G81: Expense | H81: =IF(G81<>F81,"YES","NO")
A82: 45699 | B82: Card Withdrawals - ATM Withdrawal 1291 OLD BALDWIN NEW ATHENS IL | C82: 203.25 | D82: Debit | E82: Tools | F82: =IF(E82="Income","Revenue",IF(OR(E82="Materials",E82="Labor",E82="Dump Fees"),"COGS",IF(OR(E82="Fuel",E82="Insurance",E82="Tools",E82="Repairs"),"Expense","Non-Deductible"))) | G82: Expense | H82: =IF(G82<>F82,"YES","NO")
A83: 45699 | B83: Card Withdrawals - Fee ATM Withdrawal At Other Network 1100000109 | C83: 2.5 | D83: Debit | E83: Tools | F83: =IF(E83="Income","Revenue",IF(OR(E83="Materials",E83="Labor",E83="Dump Fees"),"COGS",IF(OR(E83="Fuel",E83="Insurance",E83="Tools",E83="Repairs"),"Expense","Non-Deductible"))) | G83: Expense | H83: =IF(G83<>F83,"YES","NO")
A84: 45700 | B84: Card Withdrawals - Debit Purchase DOLLAR-GENERAL # FREEBURG IL 9502121134 | C84: 77.55 | D84: Debit | E84: Tools | F84: =IF(E84="Income","Revenue",IF(OR(E84="Materials",E84="Labor",E84="Dump Fees"),"COGS",IF(OR(E84="Fuel",E84="Insurance",E84="Tools",E84="Repairs"),"Expense","Non-Deductible"))) | G84: Expense | H84: =IF(G84<>F84,"YES","NO")
A85: 45700 | B85: Other Withdrawals - Zelle Instant PMT To Tabitha Session | C85: 182 | D85: Debit | E85: Tools | F85: =IF(E85="Income","Revenue",IF(OR(E85="Materials",E85="Labor",E85="Dump Fees"),"COGS",IF(OR(E85="Fuel",E85="Insurance",E85="Tools",E85="Repairs"),"Expense","Non-Deductible"))) | G85: Expense | H85: =IF(G85<>F85,"YES","NO")
A86: 45701 | B86: Card Withdrawals - Debit Purchase - VISA On 021225 BELLEVILLE IL 4106251248 | C86: 39.45 | D86: Debit | E86: Tools | F86: =IF(E86="Income","Revenue",IF(OR(E86="Materials",E86="Labor",E86="Dump Fees"),"COGS",IF(OR(E86="Fuel",E86="Insurance",E86="Tools",E86="Repairs"),"Expense","Non-Deductible"))) | G86: Expense | H86: =IF(G86<>F86,"YES","NO")
... A90: 45702 | B90: Other Withdrawals - Mobile Banking Transfer To Account 152316875235 | C90: 550 | D90: Debit | E90: Transfer | F90: =IF(E90="Income","Revenue",IF(OR(E90="Materials",E90="Labor",E90="Dump Fees"),"COGS",IF(OR(E90="Fuel",E90="Insurance",E90="Tools",E90="Repairs"),"Expense","Non-Deductible"))) | G90: Non-Deductible | H90: =IF(G90<>F90,"YES","NO")
A91: 45702 | B91: Other Withdrawals - Zelle Instant PMT To Brian Davis | C91: 1170 | D91: Debit | E91: Labor | F91: =IF(E91="Income","Revenue",IF(OR(E91="Materials",E91="Labor",E91="Dump Fees"),"COGS",IF(OR(E91="Fuel",E91="Insurance",E91="Tools",E91="Repairs"),"Expense","Non-Deductible"))) | G91: COGS | H91: =IF(G91<>F91,"YES","NO") | J91: Bryan
A92: 45702 | B92: Other Withdrawals - Zelle Instant PMT To Casey Williamson | C92: 800 | D92: Debit | E92: Labor | F92: =IF(E92="Income","Revenue",IF(OR(E92="Materials",E92="Labor",E92="Dump Fees"),"COGS",IF(OR(E92="Fuel",E92="Insurance",E92="Tools",E92="Repairs"),"Expense","Non-Deductible"))) | G92: COGS | H92: =IF(G92<>F92,"YES","NO") | J92: Casey
A93: 45702 | B93: Other Withdrawals - Zelle Instant PMT To Nadia Session | C93: 100 | D93: Debit | E93: Tools | F93: =IF(E93="Income","Revenue",IF(OR(E93="Materials",E93="Labor",E93="Dump Fees"),"COGS",IF(OR(E93="Fuel",E93="Insurance",E93="Tools",E93="Repairs"),"Expense","Non-Deductible"))) | G93: Expense | H93: =IF(G93<>F93,"YES","NO")
A94: 45706 | B94: Card Withdrawals - Debit Purchase verifyvend855-55 PROVIDENCE RI 5402171314 | C94: 57 | D94: Debit | E94: Tools | F94: =IF(E94="Income","Revenue",IF(OR(E94="Materials",E94="Labor",E94="Dump Fees"),"COGS",IF(OR(E94="Fuel",E94="Insurance",E94="Tools",E94="Repairs"),"Expense","Non-Deductible"))) | G94: Expense | H94: =IF(G94<>F94,"YES","NO")
A95: 45707 | B95: Card Withdrawals - Debit Purchase - VISA On 021825 BELLEVILLE IL 9300620697 | C95: 31.37 | D95: Debit | E95: Tools | F95: =IF(E95="Income","Revenue",IF(OR(E95="Materials",E95="Labor",E95="Dump Fees"),"COGS",IF(OR(E95="Fuel",E95="Insurance",E95="Tools",E95="Repairs"),"Expense","Non-Deductible"))) | G95: Expense | H95: =IF(G95<>F95,"YES","NO")
A96: 45707 | B96: Card Withdrawals - Debit Purchase MOTOMART FREEBURG IL | C96: 81.6 | D96: Debit | E96: Tools | F96: =IF(E96="Income","Revenue",IF(OR(E96="Materials",E96="Labor",E96="Dump Fees"),"COGS",IF(OR(E96="Fuel",E96="Insurance",E96="Tools",E96="Repairs"),"Expense","Non-Deductible"))) | G96: Expense | H96: =IF(G96<>F96,"YES","NO")
A97: 45707 | B97: Other Withdrawals - Electronic Withdrawal To CATHOLIC CCU | C97: 572.5 | D97: Debit | E97: Tools | F97: =IF(E97="Income","Revenue",IF(OR(E97="Materials",E97="Labor",E97="Dump Fees"),"COGS",IF(OR(E97="Fuel",E97="Insurance",E97="Tools",E97="Repairs"),"Expense","Non-Deductible"))) | G97: Expense | H97: =IF(G97<>F97,"YES","NO")
A98: 45708 | B98: Card Withdrawals - Debit Purchase HI-WAY LMB CO NEW ATHENS IL 8102201546 | C98: 25.95 | D98: Debit | E98: Tools | F98: =IF(E98="Income","Revenue",IF(OR(E98="Materials",E98="Labor",E98="Dump Fees"),"COGS",IF(OR(E98="Fuel",E98="Insurance",E98="Tools",E98="Repairs"),"Expense","Non-Deductible"))) | G98: Expense | H98: =IF(G98<>F98,"YES","NO")
A99: 45708 | B99: Other Withdrawals - Electronic Withdrawal To MERCURY CARD FBT | C99: 670.41 | D99: Debit | E99: Tools | F99: =IF(E99="Income","Revenue",IF(OR(E99="Materials",E99="Labor",E99="Dump Fees"),"COGS",IF(OR(E99="Fuel",E99="Insurance",E99="Tools",E99="Repairs"),"Expense","Non-Deductible"))) | G99: Expense | H99: =IF(G99<>F99,"YES","NO")
A100: 45709 | B100: Other Withdrawals - Mobile Banking Transfer To Account 152316874980 | C100: 750 | D100: Debit | E100: Transfer | F100: =IF(E100="Income","Revenue",IF(OR(E100="Materials",E100="Labor",E100="Dump Fees"),"COGS",IF(OR(E100="Fuel",E100="Insurance",E100="Tools",E100="Repairs"),"Expense","Non-Deductible"))) | G100: Non-Deductible | H100: =IF(G100<>F100,"YES","NO")
A101: 45709 | B101: Other Withdrawals - Zelle Instant PMT To BRIAN DAVIS | C101: 580 | D101: Debit | E101: Labor | F101: =IF(E101="Income","Revenue",IF(OR(E101="Materials",E101="Labor",E101="Dump Fees"),"COGS",IF(OR(E101="Fuel",E101="Insurance",E101="Tools",E101="Repairs"),"Expense","Non-Deductible"))) | G101: COGS | H101: =IF(G101<>F101,"YES","NO") | J101: Bryan
A102: 45709 | B102: Other Withdrawals - Zelle Instant PMT To CASEY WILLIAMSON | C102: 400 | D102: Debit | E102: Labor | F102: =IF(E102="Income","Revenue",IF(OR(E102="Materials",E102="Labor",E102="Dump Fees"),"COGS",IF(OR(E102="Fuel",E102="Insurance",E102="Tools",E102="Repairs"),"Expense","Non-Deductible"))) | G102: COGS | H102: =IF(G102<>F102,"YES","NO") | J102: Casey
A103: 45712 | B103: Card Withdrawals - Debit Purchase - VISA On 022025 SWANSEA IL 2004371665 | C103: 81.54 | D103: Debit | E103: Tools | F103: =IF(E103="Income","Revenue",IF(OR(E103="Materials",E103="Labor",E103="Dump Fees"),"COGS",IF(OR(E103="Fuel",E103="Insurance",E103="Tools",E103="Repairs"),"Expense","Non-Deductible"))) | G103: Expense | H103: =IF(G103<>F103,"YES","NO")
A104: 45714 | B104: Card Withdrawals - Recurring Debit Purchase On 022525 888-270-2644 IN 6106932422 | C104: 817.5 | D104: Debit | E104: Tools | F104: =IF(E104="Income","Revenue",IF(OR(E104="Materials",E104="Labor",E104="Dump Fees"),"COGS",IF(OR(E104="Fuel",E104="Insurance",E104="Tools",E104="Repairs"),"Expense","Non-Deductible"))) | G104: Expense | H104: =IF(G104<>F104,"YES","NO")
A105: 45714 | B105: Other Withdrawals - Electronic Withdrawal To DISCOVER | C105: 2000 | D105: Debit | E105: Tools | F105: =IF(E105="Income","Revenue",IF(OR(E105="Materials",E105="Labor",E105="Dump Fees"),"COGS",IF(OR(E105="Fuel",E105="Insurance",E105="Tools",E105="Repairs"),"Expense","Non-Deductible"))) | G105: Expense | H105: =IF(G105<>F105,"YES","NO")
A106: 45715 | B106: Card Withdrawals - Debit Purchase MOTOMART FREEBURG IL | C106: 83.32 | D106: Debit | E106: Tools | F106: =IF(E106="Income","Revenue",IF(OR(E106="Materials",E106="Labor",E106="Dump Fees"),"COGS",IF(OR(E106="Fuel",E106="Insurance",E106="Tools",E106="Repairs"),"Expense","Non-Deductible"))) | G106: Expense | H106: =IF(G106<>F106,"YES","NO")
A107: 45716 | B107: Other Withdrawals - Mobile Banking Transfer To Account 152316875235 | C107: 550 | D107: Debit | E107: Transfer | F107: =IF(E107="Income","Revenue",IF(OR(E107="Materials",E107="Labor",E107="Dump Fees"),"COGS",IF(OR(E107="Fuel",E107="Insurance",E107="Tools",E107="Repairs"),"Expense","Non-Deductible"))) | G107: Non-Deductible | H107: =IF(G107<>F107,"YES","NO")
A108: 45716 | B108: Other Withdrawals - Zelle Instant PMT To Brian Davis | C108: 1300 | D108: Debit | E108: Labor | F108: =IF(E108="Income","Revenue",IF(OR(E108="Materials",E108="Labor",E108="Dump Fees"),"COGS",IF(OR(E108="Fuel",E108="Insurance",E108="Tools",E108="Repairs"),"Expense","Non-Deductible"))) | G108: COGS | H108: =IF(G108<>F108,"YES","NO") | J108: Bryan
A109: 45716 | B109: Other Withdrawals - Zelle Instant PMT To Casey Williamson | C109: 613 | D109: Debit | E109: Labor | F109: =IF(E109="Income","Revenue",IF(OR(E109="Materials",E109="Labor",E109="Dump Fees"),"COGS",IF(OR(E109="Fuel",E109="Insurance",E109="Tools",E109="Repairs"),"Expense","Non-Deductible"))) | G109: COGS | H109: =IF(G109<>F109,"YES","NO") | J109: Casey
A110: 45716 | B110: Other Withdrawals - Zelle Instant PMT To Nadia Session | C110: 100 | D110: Debit | E110: Tools | F110: =IF(E110="Income","Revenue",IF(OR(E110="Materials",E110="Labor",E110="Dump Fees"),"COGS",IF(OR(E110="Fuel",E110="Insurance",E110="Tools",E110="Repairs"),"Expense","Non-Deductible"))) | G110: Expense | H110: =IF(G110<>F110,"YES","NO")
A111: 45716 | B111: Other Withdrawals - Zelle Instant PMT To Nadia Session | C111: 400 | D111: Debit | E111: Tools | F111: =IF(E111="Income","Revenue",IF(OR(E111="Materials",E111="Labor",E111="Dump Fees"),"COGS",IF(OR(E111="Fuel",E111="Insurance",E111="Tools",E111="Repairs"),"Expense","Non-Deductible"))) | G111: Expense | H111: =IF(G111<>F111,"YES","NO")
A112: 45719 | B112: Card Withdrawals - Recurring Debit Purchase On 030125 800-956-6310 IL 0159232300 $ | C112: 328.77 | D112: Debit | E112: Tools | F112: =IF(E112="Income","Revenue",IF(OR(E112="Materials",E112="Labor",E112="Dump Fees"),"COGS",IF(OR(E112="Fuel",E112="Insurance",E112="Tools",E112="Repairs"),"Expense","Non-Deductible"))) | G112: Expense | H112: =IF(G112<>F112,"YES","NO")
A113: 45719 | B113: Other Withdrawals - Electronic Withdrawal To MERCURY CARD FBT $ | C113: 610.09 | D113: Debit | E113: Tools | F113: =IF(E113="Income","Revenue",IF(OR(E113="Materials",E113="Labor",E113="Dump Fees"),"COGS",IF(OR(E113="Fuel",E113="Insurance",E113="Tools",E113="Repairs"),"Expense","Non-Deductible"))) | G113: Expense | H113: =IF(G113<>F113,"YES","NO")
A114: 45720 | B114: Other Deposits - Visa Direct VENMO*Session Wi 6803031840 $ | C114: 3575 | D114: Credit | E114: Income | F114: =IF(E114="Income","Revenue",IF(OR(E114="Materials",E114="Labor",E114="Dump Fees"),"COGS",IF(OR(E114="Fuel",E114="Insurance",E114="Tools",E114="Repairs"),"Expense","Non-Deductible"))) | G114: Revenue | H114: =IF(G114<>F114,"YES","NO")
...

Sheet P&L_2025
A1: ALL PRO METRO EAST CONSTRUCTION LLC - Profit & Loss 2025
A3: Revenue | B3: =SUMIFS(CATEGORIZED_2025!$C:$C,CATEGORIZED_2025!$G:$G,"Revenue")
A4: COGS | B4: =SUMIFS(CATEGORIZED_2025!$C:$C,CATEGORIZED_2025!$G:$G,"COGS")
A5: Expenses | B5: =SUMIFS(CATEGORIZED_2025!$C:$C,CATEGORIZED_2025!$G:$G,"Expense")
A6: Non-Deductible | B6: =SUMIFS(CATEGORIZED_2025!$C:$C,CATEGORIZED_2025!$G:$G,"Non-Deductible")
A7: Net Income | B7: =B3-B4-B5
A8: Manual Overrides | B8: =COUNTIF(CATEGORIZED_2025!$H:$H,"YES")

Sheet MONTHLY_2025
A1: Month | B1: Revenue | C1: COGS | D1: Expenses | E1: Net Income
A2: January | B2: =SUMPRODUCT((CATEGORIZED_2025!$G$2:$G$200000="Revenue")*(TEXT(CATEGORIZED_2025!$A$2:$A$200000,"yyyy-mm")="2025-01")*CATEGORIZED_2025!$C$2:$C$200000) | C2: =SUMPRODUCT((CATEGORIZED_2025!$G$2:$G$200000="COGS")*(TEXT(CATEGORIZED_2025!$A$2:$A$200000,"yyyy-mm")="2025-01")*CATEGORIZED_2025!$C$2:$C$200000) | D2: =SUMPRODUCT((CATEGORIZED_2025!$G$2:$G$200000="Expense")*(TEXT(CATEGORIZED_2025!$A$2:$A$200000,"yyyy-mm")="2025-01")*CATEGORIZED_2025!$C$2:$C$200000) | E2: =B2-C2-D2
A3: February | B3: =SUMPRODUCT((CATEGORIZED_2025!$G$2:$G$200000="Revenue")*(TEXT(CATEGORIZED_2025!$A$2:$A$200000,"yyyy-mm")="2025-02")*CATEGORIZED_2025!$C$2:$C$200000) | C3: =SUMPRODUCT((CATEGORIZED_2025!$G$2:$G$200000="COGS")*(TEXT(CATEGORIZED_2025!$A$2:$A$200000,"yyyy-mm")="2025-02")*CATEGORIZED_2025!$C$2:$C$200000) | D3: =SUMPRODUCT((CATEGORIZED_2025!$G$2:$G$200000="Expense")*(TEXT(CATEGORIZED_2025!$A$2:$A$200000,"yyyy-mm")="2025-02")*CATEGORIZED_2025!$C$2:$C$200000) | E3: =B3-C3-D3
A4: March | B4: =SUMPRODUCT((CATEGORIZED_2025!$G$2:$G$200000="Revenue")*(TEXT(CATEGORIZED_2025!$A$2:$A$200000,"yyyy-mm")="2025-03")*CATEGORIZED_2025!$C$2:$C$200000) | C4: =SUMPRODUCT((CATEGORIZED_2025!$G$2:$G$200000="COGS")*(TEXT(CATEGORIZED_2025!$A$2:$A$200000,"yyyy-mm")="2025-03")*CATEGORIZED_2025!$C$2:$C$200000) | D4: =SUMPRODUCT((CATEGORIZED_2025!$G$2:$G$200000="Expense")*(TEXT(CATEGORIZED_2025!$A$2:$A$200000,"yyyy-mm")="2025-03")*CATEGORIZED_2025!$C$2:$C$200000) | E4: =B4-C4-D4
A5: April | B5: =SUMPRODUCT((CATEGORIZED_2025!$G$2:$G$200000="Revenue")*(TEXT(CATEGORIZED_2025!$A$2:$A$200000,"yyyy-mm")="2025-04")*CATEGORIZED_2025!$C$2:$C$200000) | C5: =SUMPRODUCT((CATEGORIZED_2025!$G$2:$G$200000="COGS")*(TEXT(CATEGORIZED_2025!$A$2:$A$200000,"yyyy-mm")="2025-04")*CATEGORIZED_2025!$C$2:$C$200000) | D5: =SUMPRODUCT((CATEGORIZED_2025!$G$2:$G$200000="Expense")*(TEXT(CATEGORIZED_2025!$A$2:$A$200000,"yyyy-mm")="2025-04")*CATEGORIZED_2025!$C$2:$C$200000) | E5: =B5-C5-D5
A6: May | B6: =SUMPRODUCT((CATEGORIZED_2025!$G$2:$G$200000="Revenue")*(TEXT(CATEGORIZED_2025!$A$2:$A$200000,"yyyy-mm")="2025-05")*CATEGORIZED_2025!$C$2:$C$200000) | C6: =SUMPRODUCT((CATEGORIZED_2025!$G$2:$G$200000="COGS")*(TEXT(CATEGORIZED_2025!$A$2:$A$200000,"yyyy-mm")="2025-05")*CATEGORIZED_2025!$C$2:$C$200000) | D6: =SUMPRODUCT((CATEGORIZED_2025!$G$2:$G$200000="Expense")*(TEXT(CATEGORIZED_2025!$A$2:$A$200000,"yyyy-mm")="2025-05")*CATEGORIZED_2025!$C$2:$C$200000) | E6: =B6-C6-D6
A7: June | B7: =SUMPRODUCT((CATEGORIZED_2025!$G$2:$G$200000="Revenue")*(TEXT(CATEGORIZED_2025!$A$2:$A$200000,"yyyy-mm")="2025-06")*CATEGORIZED_2025!$C$2:$C$200000) | C7: =SUMPRODUCT((CATEGORIZED_2025!$G$2:$G$200000="COGS")*(TEXT(CATEGORIZED_2025!$A$2:$A$200000,"yyyy-mm")="2025-06")*CATEGORIZED_2025!$C$2:$C$200000) | D7: =SUMPRODUCT((CATEGORIZED_2025!$G$2:$G$200000="Expense")*(TEXT(CATEGORIZED_2025!$A$2:$A$200000,"yyyy-mm")="2025-06")*CATEGORIZED_2025!$C$2:$C$200000) | E7: =B7-C7-D7
A8: July | B8: =SUMPRODUCT((CATEGORIZED_2025!$G$2:$G$200000="Revenue")*(TEXT(CATEGORIZED_2025!$A$2:$A$200000,"yyyy-mm")="2025-07")*CATEGORIZED_2025!$C$2:$C$200000) | C8: =SUMPRODUCT((CATEGORIZED_2025!$G$2:$G$200000="COGS")*(TEXT(CATEGORIZED_2025!$A$2:$A$200000,"yyyy-mm")="2025-07")*CATEGORIZED_2025!$C$2:$C$200000) | D8: =SUMPRODUCT((CATEGORIZED_2025!$G$2:$G$200000="Expense")*(TEXT(CATEGORIZED_2025!$A$2:$A$200000,"yyyy-mm")="2025-07")*CATEGORIZED_2025!$C$2:$C$200000) | E8: =B8-C8-D8
A9: August | B9: =SUMPRODUCT((CATEGORIZED_2025!$G$2:$G$200000="Revenue")*(TEXT(CATEGORIZED_2025!$A$2:$A$200000,"yyyy-mm")="2025-08")*CATEGORIZED_2025!$C$2:$C$200000) | C9: =SUMPRODUCT((CATEGORIZED_2025!$G$2:$G$200000="COGS")*(TEXT(CATEGORIZED_2025!$A$2:$A$200000,"yyyy-mm")="2025-08")*CATEGORIZED_2025!$C$2:$C$200000) | D9: =SUMPRODUCT((CATEGORIZED_2025!$G$2:$G$200000="Expense")*(TEXT(CATEGORIZED_2025!$A$2:$A$200000,"yyyy-mm")="2025-08")*CATEGORIZED_2025!$C$2:$C$200000) | E9: =B9-C9-D9
A10: September | B10: =SUMPRODUCT((CATEGORIZED_2025!$G$2:$G$200000="Revenue")*(TEXT(CATEGORIZED_2025!$A$2:$A$200000,"yyyy-mm")="2025-09")*CATEGORIZED_2025!$C$2:$C$200000) | C10: =SUMPRODUCT((CATEGORIZED_2025!$G$2:$G$200000="COGS")*(TEXT(CATEGORIZED_2025!$A$2:$A$200000,"yyyy-mm")="2025-09")*CATEGORIZED_2025!$C$2:$C$200000) | D10: =SUMPRODUCT((CATEGORIZED_2025!$G$2:$G$200000="Expense")*(TEXT(CATEGORIZED_2025!$A$2:$A$200000,"yyyy-mm")="2025-09")*CATEGORIZED_2025!$C$2:$C$200000) | E10: =B10-C10-D10
A11: October | B11: =SUMPRODUCT((CATEGORIZED_2025!$G$2:$G$200000="Revenue")*(TEXT(CATEGORIZED_2025!$A$2:$A$200000,"yyyy-mm")="2025-10")*CATEGORIZED_2025!$C$2:$C$200000) | C11: =SUMPRODUCT((CATEGORIZED_2025!$G$2:$G$200000="COGS")*(TEXT(CATEGORIZED_2025!$A$2:$A$200000,"yyyy-mm")="2025-10")*CATEGORIZED_2025!$C$2:$C$200000) | D11: =SUMPRODUCT((CATEGORIZED_2025!$G$2:$G$200000="Expense")*(TEXT(CATEGORIZED_2025!$A$2:$A$200000,"yyyy-mm")="2025-10")*CATEGORIZED_2025!$C$2:$C$200000) | E11: =B11-C11-D11
A12: November | B12: =SUMPRODUCT((CATEGORIZED_2025!$G$2:$G$200000="Revenue")*(TEXT(CATEGORIZED_2025!$A$2:$A$200000,"yyyy-mm")="2025-11")*CATEGORIZED_2025!$C$2:$C$200000) | C12: =SUMPRODUCT((CATEGORIZED_2025!$G$2:$G$200000="COGS")*(TEXT(CATEGORIZED_2025!$A$2:$A$200000,"yyyy-mm")="2025-11")*CATEGORIZED_2025!$C$2:$C$200000) | D12: =SUMPRODUCT((CATEGORIZED_2025!$G$2:$G$200000="Expense")*(TEXT(CATEGORIZED_2025!$A$2:$A$200000,"yyyy-mm")="2025-11")*CATEGORIZED_2025!$C$2:$C$200000) | E12: =B12-C12-D12
A13: December | B13: =SUMPRODUCT((CATEGORIZED_2025!$G$2:$G$200000="Revenue")*(TEXT(CATEGORIZED_2025!$A$2:$A$200000,"yyyy-mm")="2025-12")*CATEGORIZED_2025!$C$2:$C$200000) | C13: =SUMPRODUCT((CATEGORIZED_2025!$G$2:$G$200000="COGS")*(TEXT(CATEGORIZED_2025!$A$2:$A$200000,"yyyy-mm")="2025-12")*CATEGORIZED_2025!$C$2:$C$200000) | D13: =SUMPRODUCT((CATEGORIZED_2025!$G$2:$G$200000="Expense")*(TEXT(CATEGORIZED_2025!$A$2:$A$200000,"yyyy-mm")="2025-12")*CATEGORIZED_2025!$C$2:$C$200000) | E13: =B13-C13-D13

Sheet LABOR_2025
A1: Contractor | B1: Total
A2: Bryan | B2: =SUMIFS(CATEGORIZED_2025!$C:$C,CATEGORIZED_2025!$E:$E,"Labor",CATEGORIZED_2025!$J:$J,A2)
A3: Jameson | B3: =SUMIFS(CATEGORIZED_2025!$C:$C,CATEGORIZED_2025!$E:$E,"Labor",CATEGORIZED_2025!$J:$J,A3)
A4: Casey | B4: =SUMIFS(CATEGORIZED_2025!$C:$C,CATEGORIZED_2025!$E:$E,"Labor",CATEGORIZED_2025!$J:$J,A4)
A5: Tony | B5: =SUMIFS(CATEGORIZED_2025!$C:$C,CATEGORIZED_2025!$E:$E,"Labor",CATEGORIZED_2025!$J:$J,A5)
